ant_cli-0.0.1.data/scripts/ant
ant_cli-0.0.1.dist-info/METADATA
ant_cli-0.0.1.dist-info/RECORD
ant_cli-0.0.1.dist-info/WHEEL
ant_cli-0.0.1.dist-info/top_level.txt
ant_pkg/__init__.py
ant_pkg/ant.py
ant_pkg/config.yaml
ant_pkg/constants.py
ant_pkg/context.py
ant_pkg/responses.py
ant_pkg/commands/__init__.py
ant_pkg/commands/scaffold:assemble.py
ant_pkg/commands/scaffold:list.py
ant_pkg/commands/scaffold:update.py
ant_pkg/utils/__init__.py
ant_pkg/utils/dir.py
ant_pkg/utils/file.py
ant_pkg/utils/logger.py
ant_pkg/utils/try_execpt.py
